{"Adana":481.47,"Ad\u0131yaman":98.66,"Afyon":364.9,"A\u011fr\u0131":367.18,"Aksaray":180.37,"Amasya":359.17,"Ankara":1003.3,"Antalya":118.55,"Ardahan":410.77,"Artvin":469.61,"Ayd\u0131n":401.94,"Bal\u0131kesir":597.69,"Bart\u0131n":567.4,"Batman":484.46,"Bayburt":533.51,"Bilecik":628.21,"Bing\u00f6l":266.18,"Bitlis":448.44,"Bolu":879.6,"Burdur":447.41,"Bursa":928.81,"\u00c7anakkale":716.46,"\u00c7ank\u0131r\u0131":713.51,"\u00c7orum":521.76,"Denizli":442.59,"Diyarbak\u0131r":475.54,"D\u00fczce":592.9,"Edirne":537.57,"Elaz\u0131\u011f":800.39,"Erzincan":491.4,"Erzurum":763.57,"Eski\u015fehir":625.88,"Gaziantep":182.99,"Giresun":920.17,"G\u00fcm\u00fc\u015fhane":378.26,"Hakkari":277.35,"Hatay":230.03,"I\u011fd\u0131r":585.16,"Isparta":570.06,"\u0130stanbul":889.58,"\u0130zmir":961.57,"Kahramanmara\u015f":292,"Karab\u00fck":663.75,"Karaman":295.39,"Kars":425.38,"Kastamonu":649.88,"Kayseri":555.28,"K\u0131r\u0131kkale":693.57,"K\u0131rklareli":1214.42,"K\u0131r\u015fehir":371.95,"Kilis":302.54,"Kocaeli":1042.28,"Konya":500.71,"K\u00fctahya":601.37,"Malatya":253.8,"Manisa":724.18,"Mardin":270.73,"Mersin":364.09,"Mu\u011fla":652.9,"Mu\u015f":366.08,"Nev\u015fehir":436.12,"Ni\u011fde":298.01,"Ordu":715.79,"Osmaniye":261.78,"Rize":997.51,"Sakarya":651.42,"Samsun":704.83,"Siirt":528.59,"Sinop":687.89,"Sivas":486.56,"\u015eanl\u0131urfa":119.18,"\u015e\u0131rnak":146.16,"Tekirda\u011f":1020.01,"Tokat":743.65,"Trabzon":853.31,"Tunceli":695.09,"U\u015fak":794.46,"Van":60.9,"Yalova":962.14,"Yozgat":394.42,"Zonguldak":528.41}